nvy/__init__.py
nvy-0.0.1.dist-info/LICENSE
nvy-0.0.1.dist-info/METADATA
nvy-0.0.1.dist-info/WHEEL
nvy-0.0.1.dist-info/entry_points.txt
nvy-0.0.1.dist-info/top_level.txt
nvy-0.0.1.dist-info/RECORD
