Metadata-Version: 2.1
Name: nvy
Version: 0.0.1
Summary: CLI the the Python venv module
Home-page: UNKNOWN
Author: Koen Woortman
Author-email: koensw@outlook.com
License: MIT
Platform: UNKNOWN
Classifier: Programming Language :: Python :: 3
Classifier: License :: OSI Approved :: MIT License
Classifier: Operating System :: OS Independent
Classifier: Environment :: Console
